{
  "id": "nexus-onboarding-eoy",
  "title": "Nexus Walkthrough — Regional Food Bank (EOY)",
  "version": 2,
  "completionStorageKey": "nexusTutorialComplete",
  "steps": [
    {
      "id": "welcome",
      "type": "modal",
      "title": "Welcome to Nexus",
      "body": "This walkthrough will create a real campaign end to end. We will start in Clients, then create or select a client, create a campaign, build it, review, launch, monitor, and report.",
      "primaryCta": "Start Walkthrough",
      "secondaryCta": "Skip tutorial",
      "secondaryAction": "dismiss"
    },
    {
      "id": "go-to-clients",
      "type": "spotlight",
      "navigateTo": "/clients",
      "anchors": ["[data-tutorial-step='nav.clients']", "[data-tutorial-step='clients.page']"],
      "title": "Open Clients",
      "body": "All work begins here. Click Clients in the sidebar to view or create organizations.",
      "primaryCta": "Next"
    },
    {
      "id": "create-or-select-client",
      "type": "spotlight",
      "anchors": ["[data-tutorial-step='clients.add']", "[data-tutorial-step='clients.table.row.regional-food-bank']"],
      "waitForAnchorMs": 6000,
      "title": "Create or select a client",
      "body": "Option A: Click New Client to create Regional Food Bank. Option B: If Regional Food Bank already exists, click it to open.",
      "tip": "In demo mode we seed Regional Food Bank so you can select it immediately.",
      "primaryCta": "I did this"
    },
    {
      "id": "client-home",
      "type": "spotlight",
      "anchors": ["[data-tutorial-step='client.header']", "[data-tutorial-step='client.campaigns.tab']"],
      "title": "Client workspace",
      "body": "You are now inside the client workspace. Each client has its own campaigns, assets, and reports.",
      "primaryCta": "Next"
    },
    {
      "id": "new-campaign",
      "type": "spotlight",
      "anchors": ["[data-tutorial-step='campaigns.new']"],
      "title": "Create a campaign",
      "body": "Click New Campaign. Use these defaults: Name End-of-Year Holiday Campaign, Goal 10000, Type End-of-Year, Dates Nov 15 to Dec 31, Theme Holiday Warmth and Community Generosity.",
      "primaryCta": "Create Campaign"
    },
    {
      "id": "builder",
      "type": "spotlight",
      "anchors": ["[data-tutorial-step='campaign.builder']"],
      "title": "Build the plan",
      "body": "Add overview, upload assets, add segments Current Donors, Lapsed Donors, Volunteers, assign collaborators if needed.",
      "tip": "Import your Track15 templates to prefill calendars and tags.",
      "primaryCta": "Save and continue"
    },
    {
      "id": "review",
      "type": "spotlight",
      "anchors": ["[data-tutorial-step='campaign.review']"],
      "title": "Review and launch",
      "body": "Confirm assets, segments, and the goal 10000. Set launch date to Nov 15. Launch when ready. Nexus begins tracking metrics automatically.",
      "primaryCta": "Launch Campaign"
    },
    {
      "id": "monitor",
      "type": "spotlight",
      "navigateTo": "/dashboard",
      "anchors": ["[data-tutorial-step='dashboard.performance']"],
      "title": "Monitor performance",
      "body": "Track total raised, donor growth, channel mix, and milestones in real time.",
      "primaryCta": "Next"
    },
    {
      "id": "reports",
      "type": "spotlight",
      "navigateTo": "/reports",
      "anchors": ["[data-tutorial-step='reports.panel']"],
      "title": "Create reports",
      "body": "Generate share-ready PDFs, export CSVs, or schedule weekly summaries.",
      "primaryCta": "Generate sample report"
    },
    {
      "id": "optimize",
      "type": "spotlight",
      "navigateTo": "/campaigns",
      "anchors": ["[data-tutorial-step='campaigns.list']"],
      "title": "Optimize and repeat",
      "body": "Duplicate top performers next year and keep iterating.",
      "primaryCta": "Finish",
      "secondaryCta": "Restart tour",
      "secondaryAction": "restart"
    }
  ],
  "demoSeeds": {
    "clientSlug": "regional-food-bank",
    "campaignSlug": "eoy-holiday-2025"
  }
}
